[
    {   
      "id": 10,
      "name": "hua",
      "des": "这就是生活吧",
      "like": 20,
      "collect": [1,2],
      "imgUrl": "http://p8tc04lo6.bkt.clouddn.com/alive.jpeg",
      "authorUrl": "http://p8tc04lo6.bkt.clouddn.com/bizhi.jpeg",
      "albumUrl": "http://p8tc04lo6.bkt.clouddn.com/peiban.jpeg"
    },
    {   
      "id": 20,
      "name": "cicistream",
      "des": "一个动漫男孩",
      "like": 10,
      "collect": [3,4],
      "imgUrl": "http://p8tc04lo6.bkt.clouddn.com/boy.jpeg",
      "authorUrl": "http://p8tc04lo6.bkt.clouddn.com/me.jpg",
      "albumUrl": ""
    },
    {   
      "id": 30,
      "name": "cici",
      "des": "bad liar专辑",
      "like": 10,
      "collect": [5,6],
      "imgUrl": "http://p8tc04lo6.bkt.clouddn.com/badliar.jpeg",
      "authorUrl": "http://p8tc04lo6.bkt.clouddn.com/f1ae2d461da82a29622ca93c5f379bf97a01ebd9adf1-uM1Gbk_fw658.jpeg",
      "albumUrl": "http://p8tc04lo6.bkt.clouddn.com/pingmian.jpg"
    },
    {   
      "id": 40,
      "name": "Iris",
      "des": "云养猫~喵喵~",
      "like": 10,
      "collect": [7,8],
      "imgUrl": "http://p8tc04lo6.bkt.clouddn.com/pet.jpeg",
      "authorUrl": "http://p8tc04lo6.bkt.clouddn.com/f1ae2d461da82a29622ca93c5f379bf97a01ebd9adf1-uM1Gbk_fw658.jpeg",
      "albumUrl": "http://p8tc04lo6.bkt.clouddn.com/pingmian.jpg"
    },
    {   
      "id": 50,
      "name": "cicistream",
      "des": "陪伴",
      "like": 2,
      "collect": [3,4],
      "imgUrl": "http://p8tc04lo6.bkt.clouddn.com/peiban.jpeg",
      "authorUrl": "http://p8tc04lo6.bkt.clouddn.com/me.jpg",
      "albumUrl": "http://p8tc04lo6.bkt.clouddn.com/pingmian.jpg"
    },
    {   
      "id": 60,
      "name": "cicistream",
      "des": "也许是未来的路",
      "like": 21,
      "collect": [3,4],
      "imgUrl": "http://p8tc04lo6.bkt.clouddn.com/road.jpg",
      "authorUrl": "http://p8tc04lo6.bkt.clouddn.com/me.jpg",
      "albumUrl": "http://p8tc04lo6.bkt.clouddn.com/pingmian.jpg"
    },
    {   
      "id": 70,
      "name": "coco",
      "des": "也许是未来的路",
      "like": 7,
      "collect": [4,9],
      "imgUrl": "http://p8tc04lo6.bkt.clouddn.com/we.jpg",
      "authorUrl": "http://p8tc04lo6.bkt.clouddn.com/travel.png",
      "albumUrl": "http://p8tc04lo6.bkt.clouddn.com/us.jpg"
    },
    {   
      "id": 80,
      "name": "NNSDFI",
      "des": "随意的一些收集",
      "like": 20,
      "collect": [10],
      "imgUrl": "http://p8tc04lo6.bkt.clouddn.com/plane.jpeg",
      "authorUrl": "http://p8tc04lo6.bkt.clouddn.com/portrait.jpeg",
      "albumUrl": "http://p8tc04lo6.bkt.clouddn.com/feng.jpeg"
    },
    {   
      "id": 90,
      "name": "NNSDFI",
      "des": "随意的一些收集",
      "like": 2,
      "collect": [10],
      "imgUrl": "http://p8tc04lo6.bkt.clouddn.com/feng.jpeg",
      "authorUrl": "http://p8tc04lo6.bkt.clouddn.com/portrait.jpeg",
      "albumUrl": "http://p8tc04lo6.bkt.clouddn.com/feng.jpeg"
    },
    {   
      "id": 100,
      "name": "Juno",
      "des": "关于我，关于夏天",
      "like": 3,
      "collect": [12,4],
      "imgUrl": "http://p8tc04lo6.bkt.clouddn.com/hair.jpg",
      "authorUrl": "http://p8tc04lo6.bkt.clouddn.com/he.jpg",
      "albumUrl": "http://p8tc04lo6.bkt.clouddn.com/logo.png"
    }
]
